{
    testi.. 
    "projects": [
	{
            "project": "Avoimien aineistojen tiedostopalvelu",
            "owner": "Maanmittauslaitos",
            "code_url": "https://github.com/nlsfi/file-download-service",
            "service_url": "https://tiedostopalvelu.maanmittauslaitos.fi/tp/kartta?lang=en",
            "homepage_url": "",
	    "description": "Avoimien kartta-aineistojen jakopalvelu"
	},
	{
            "project": "Avoin kartta- ja aineistopalvelu, oskari.org",
            "owner": "Maanmittauslaitos",
            "code_url": "https://github.com/nls-oskari/oskari.org",
            "service_url": "http://www.oskari.org/",
            "homepage_url": "http://www.oskari.org/",	    
	    "description": "Avoimen kartta-aineiston katseluun ja selailuun tarkoitettu asiakasohjelma"
	},
        {
            "project": "Ammatillisen aikuiskoulutuksen palautejärjestelmä Aipal",
            "owner": "Opetushallitus",
            "code_url": "https://github.com/Opetushallitus/aipal",
            "service_url": "-",
            "homepage_url": "https://confluence.csc.fi/pages/viewpage.action?pageId=53517029",
	    "description": ""
        },
        {
            "project": "Tutkintotoimikuntarekisteri Aitu",
            "owner": "Opetushallitus",
            "code_url": "https://github.com/Opetushallitus/aitu",
            "service_url": "-",
            "homepage_url": "https://confluence.csc.fi/display/OPHPALV/Tutkintotoimikuntarekisteri",
	    "description": "Tutkintotoimikuntajärjestelmän ydinjärjestelmä"
        },
        {
            "project": "Todennetun osaamisen rekisteri TOR",
            "owner": "Opetushallitus",
            "code_url": "https://github.com/Opetushallitus/tor",
            "service_url": "-",
            "homepage_url": "-",
	    "description": ""
        },
        {
            "project": "Hakurekisteri",
            "owner": "Opetushallitus",
            "code_url": "https://github.com/Opetushallitus/hakurekisteri",
            "service_url": "-",
            "homepage_url": "-",
	    "description": ""
        },
        {
            "project": "osaan.fi -palvelu",
            "owner": "Opetushallitus",
            "code_url": "https://github.com/Opetushallitus/osaan.fi",
            "service_url": "https://www.osaan.fi",
            "homepage_url": "https://confluence.csc.fi/display/OPHPALV/osaan.fi",
	    "description": "Palvelu oman ammatillisen osaamisen arvioimiseksi."
        },
        {
            "project": "näyttötutkintohaku.fi -palvelu",
            "owner": "Opetushallitus",
            "code_url": "https://github.com/Opetushallitus/aituhaku",
            "service_url": "http://www.nayttotutkintohaku.fi",
            "homepage_url": "https://confluence.csc.fi/pages/viewpage.action?pageId=58826670",
	    "description": "Palvelu näyttötutkintojen järjestäjien etsimiseen."
        },
        {
            "project": "Koodistopalvelu",
            "owner": "Opetushallitus",
            "code_url": "https://github.com/Opetushallitus/koodisto",
            "service_url": "-",
            "homepage_url": "https://confluence.csc.fi/display/OPHPALV/Koodistopalvelu",
	    "description": ""
        },
        {
            "project": "Organisaatiopalvelu",
            "owner": "Opetushallitus",
            "code_url": "https://github.com/Opetushallitus/organisaatio",
            "service_url": "-",
            "homepage_url": "https://confluence.csc.fi/display/OPHPALV/Organisaatiotietojen+hallintapalvelu",
	    "description": "Organisaatioiden hallintapalvelu"
        },
        {
            "project": "Tutkintotietojen hallinnan ePerusteet -järjestelmä",
            "owner": "Opetushallitus",
            "code_url": "https://github.com/Opetushallitus/eperusteet",
            "service_url": "https://eperusteet.opintopolku.fi/",
            "homepage_url": "-",
	    "description": "Tutkintojen viralliset muodostumissäännöt, suorituskriteerit ja sisällöt hallitaan ePerusteet-järjestelmällä."
        },
        {
            "project": "Valtionavustusten hakujärjestelmä",
            "owner": "Opetushallitus",
            "code_url": "https://github.com/Opetushallitus/valtionavustus",
            "service_url": "-",
            "homepage_url": "-",
	    "description": ""
        },
        {
            "project": "kansalaisaloite.fi -palvelu",
            "owner": "Oikeusministeriö",
            "code_url": "https://github.com/solita/kansalaisaloite",
            "service_url": "https://www.kansalaisaloite.fi/",
            "homepage_url": "-",
	    "description": ""
        },
        {
            "project": "Rakennetun ympäristön asiointipalvelu Lupapiste",
            "owner": "Ympäristöministeriö",
            "code_url": "https://github.com/lupapiste/lupapiste",
            "service_url": "https://www.lupapiste.fi/",
            "homepage_url": "-",
	    "description": "Lupapiste on sähköinen palvelu, jossa rakennus-, ympäristö- ja yleisten alueiden käyttölupiin liittyvät hakemukset ja aineistot välittyvät kunnan järjestelmiin sähköisessä muodossa. Lupapiste palvelee ensikontaktista tai neuvontapyynnöstä alkaen koko hankkeen ajan aina valmistumiseen saakka."
        },
	    {
            "project": "Tarkkailija -palvelu asuinympäristön tapahtumien seurantaan",
            "owner": "Ympäristöministeriö",
            "code_url": "https://github.com/solita/Tarkkailija",
            "service_url": "https://etarkkailija.fi/",
            "homepage_url": "-",
            "description": "Tarkkailijalla löytää tietoa valitun alueen asumisesta, kaavoituksesta, liikuntamahdollisuuksista, liikenteestä, yhdistystoiminnasta ja päätöksenteosta. Tarkkailija hakee tiedot yli 400:sta kuntien, viranomaisten ja medioiden verkkopalvelusta."
        },
        {
            "project": "Tieverkoston aineistopalvelu Digiroad",
            "owner": "Liikennevirasto",
            "code_url": "https://github.com/finnishtransportagency/digiroad2",
            "service_url": "-",
            "homepage_url": "-",
	    "description": ""
        },
        {
            "project": "Liikennetietopalvelu Digitraffic",
            "owner": "Liikennevirasto",
            "code_url": "https://github.com/finnishtransportagency/digitraffic",
            "service_url": "-",
            "homepage_url": "-",
	    "description": ""
        },
        {
            "project": "Joukkoliikenteen seurantajärjestelmä Juku",
            "owner": "Liikennevirasto",
            "code_url": "https://github.com/solita/livijuku",
            "service_url": "-",
            "homepage_url": "-",
	    "description": ""
        },
        {
            "project": "Korkeakoulujen palautejärjestelmä Arvo",
            "owner": "CSC",
            "code_url": "https://github.com/CSC-IT-Center-for-Science/arvo",
            "service_url": "-",
            "homepage_url": "-",
	    "description": ""
        },
        {
            "project": "Avoimen tiedon ja yhteentoimivuuden palvelu Avoindata.fi",
            "owner": "Valtori",
            "code_url": "https://github.com/yhteentoimivuuspalvelut/ytp",
            "service_url": "https://www.avoindata.fi/fi",
            "homepage_url": "-",
	    "description": ""
        },
        {
            "project": "Apika (PoC)",
            "owner": "Väestörekisterikeskus",
            "code_url": "https://github.com/Digipalvelutehdas/apika-dashboard",
            "service_url": "https://apika.digipalvelutehdas.fi/",
            "homepage_url": "http://apisuomi.fi/category/apika/",
	    "description": "Avoimien rajapintojen hakemisto ja hallintajärjestelmä"
        },
	{
            "project": "Palveluväylän turvapalvelin",
            "owner": "Väestörekisterikeskus",
            "code_url": "https://github.com/vrk-kpa/xroad-public",
            "service_url": "-",
            "homepage_url": "-",
	    "description": ""
	},
	{
            "project": "Liityntäkatalogi",
            "owner": "Väestörekisterikeskus",
            "code_url": "https://github.com/vrk-kpa/api-catalog",	    
            "service_url": "https://liityntakatalogi.suomi.fi/",
            "homepage_url": "-",
	    "description": ""
	},
	{
            "project": "Digitransit, Uuden ajan matkaopas",
            "owner": "HSL & Liikennevirasto",
            "code_url": "https://github.com/HSLdevcom/digitransit",	    
            "service_url": "http://beta.digitransit.fi/",
            "homepage_url": "http://digitransit.fi/",
	    "description": ""
	},
	{
            "project": "MPASS tunnistusratkaisu (beta)",
            "owner": "OKM & CSC",
            "code_url": "https://github.com/Digipalvelutehdas/MPASS-proxy",	    
            "service_url": "https://mpass-connector.csc.fi/",
            "homepage_url": "http://mpass.fi",
	    "description": "Heikkojen tunnistusmenetelmien SSO-ratkaisu"
	},
	{
            "project": "Suomi.fi-tunnistaminen",
            "owner": "Väestörekisterikeskus",
            "code_url": "https://github.com/vrk-kpa?utf8=%E2%9C%93&query=e-identification",
            "service_url": "-",
            "homepage_url": "http://esuomi.fi/palveluntarjoajille/tunnistaminen/",
	    "description": "Suomi.fi-tunnistaminen mahdollistaa Suomen ja EU-kansalaisen sähköisen tunnistamisen tietoturvallisesti erilaisia tunnistusvälineitä, kuten pankkitunnistusta ja mobiilivarmennetta hyödyntäen."
	},
	{
	    "project": "OpenStreetMap -palveluun pohjautuva palvelukartta",
	    "owner": "Helsingin kaupunki",
	    "code_url": "https://github.com/City-of-Helsinki/servicemap",
	    "service_url": " http://servicemap.hel.fi/",
	    "homepage_url": "",
	    "description": ""
	}
    ]
}
